{
    "key": "group_607db9738b95a",
    "title": "Primary Button",
    "fields": [
        {
            "key": "field_607db9795d3f1",
            "label": "Primary Button",
            "name": "primary_button",
            "type": "link",
            "instructions": "",
            "required": 0,
            "conditional_logic": 0,
            "wrapper": {
                "width": "",
                "class": "",
                "id": ""
            },
            "return_format": "array"
        },
        {
            "key": "field_607db9c1af87a",
            "label": "Align",
            "name": "align",
            "type": "select",
            "instructions": "",
            "required": 0,
            "conditional_logic": 0,
            "wrapper": {
                "width": "",
                "class": "",
                "id": ""
            },
            "choices": {
                "left": "Left",
                "center": "Center",
                "right": "Right"
            },
            "default_value": "left",
            "allow_null": 1,
            "multiple": 0,
            "ui": 1,
            "ajax": 0,
            "return_format": "value",
            "placeholder": ""
        }
    ],
    "location": [
        [
            {
                "param": "block",
                "operator": "==",
                "value": "acf\/btnprimary"
            }
        ]
    ],
    "menu_order": 0,
    "position": "normal",
    "style": "default",
    "label_placement": "top",
    "instruction_placement": "label",
    "hide_on_screen": "",
    "active": true,
    "description": "",
    "modified": 1618852364
}